README.md
setup.cfg
setup.py
splits/__init__.py
splits/readers.py
splits/s3.py
splits/test.py
splits/util.py
splits/writers.py
splits.egg-info/PKG-INFO
splits.egg-info/SOURCES.txt
splits.egg-info/dependency_links.txt
splits.egg-info/requires.txt
splits.egg-info/top_level.txt
test/test_readers.py
test/test_writers.py