Metadata-Version: 1.2
Name: splits
Version: 0.1.7
Summary: A library for dealing with splittable files
Home-page: https://github.com/stitchfix/splits
Author: Thomas Millar, Jeff Magnusson
Author-email: millar.thomas@gmail.com, magnussj@gmail.com
License: MIT
Keywords: split,multifile,splittable
Platform: UNKNOWN
Classifier: Intended Audience :: Developers
Requires-Python: >=2.7,!=3.0.*,!=3.1.*,!=3.2.*,!=3.3.*,!=3.4.*
